lightshield/__init__.py
lightshield/exceptions.py
lightshield/proxy/__init__.py
lightshield/proxy/endpoint.py
lightshield/proxy/main.py
lightshield/settings.py
lightshield-0.4.0.5b0.dist-info/LICENSE
lightshield-0.4.0.5b0.dist-info/WHEEL
lightshield-0.4.0.5b0.dist-info/METADATA
lightshield-0.4.0.5b0.dist-info/RECORD
