Metadata-Version: 2.1
Name: lightshield
Version: 0.4.0.5b0
Summary: Library part of the Lightshield tool.
Home-page: https://github.com/LightshieldDotDev/Lightshield
License: Apache-2.0
Author: Doctress
Author-email: lightshielddev@gmail.com
Requires-Python: >=3.9,<4.0
Classifier: License :: OSI Approved :: Apache Software License
Classifier: Programming Language :: Python :: 3
Classifier: Programming Language :: Python :: 3.9
Requires-Dist: aiohttp (>=3.7.4,<4.0.0)
Requires-Dist: aioredis (>=2.0.1,<3.0.0)
Project-URL: Repository, https://github.com/LightshieldDotDev/Lightshield
